<annotation>
	<folder>train</folder>
	<filename>Bathroom.56536b3a-b14e-11eb-a967-00f48dddcbd4.jpg</filename>
	<path>D:\jupyternotebooks\mainsrc\Tensorflow\workspace\images\train\Bathroom.56536b3a-b14e-11eb-a967-00f48dddcbd4.jpg</path>
	<source>
		<database>Unknown</database>
	</source>
	<size>
		<width>640</width>
		<height>480</height>
		<depth>3</depth>
	</size>
	<segmented>0</segmented>
	<object>
		<name>Bathroom</name>
		<pose>Unspecified</pose>
		<truncated>0</truncated>
		<difficult>0</difficult>
		<bndbox>
			<xmin>276</xmin>
			<ymin>164</ymin>
			<xmax>374</xmax>
			<ymax>300</ymax>
		</bndbox>
	</object>
</annotation>