<annotation>
	<folder>train</folder>
	<filename>C.ca4b27e8-ae39-11eb-8140-00f48dddcbd4.jpg</filename>
	<path>D:\jupyternotebooks\mainsrc\Tensorflow\workspace\images\train\C.ca4b27e8-ae39-11eb-8140-00f48dddcbd4.jpg</path>
	<source>
		<database>Unknown</database>
	</source>
	<size>
		<width>640</width>
		<height>480</height>
		<depth>3</depth>
	</size>
	<segmented>0</segmented>
	<object>
		<name>C</name>
		<pose>Unspecified</pose>
		<truncated>0</truncated>
		<difficult>0</difficult>
		<bndbox>
			<xmin>414</xmin>
			<ymin>155</ymin>
			<xmax>509</xmax>
			<ymax>318</ymax>
		</bndbox>
	</object>
</annotation>