<annotation>
	<folder>train</folder>
	<filename>H.18b05fe2-ae58-11eb-9342-00f48dddcbd4.jpg</filename>
	<path>D:\jupyternotebooks\mainsrc\Tensorflow\workspace\images\train\H.18b05fe2-ae58-11eb-9342-00f48dddcbd4.jpg</path>
	<source>
		<database>Unknown</database>
	</source>
	<size>
		<width>640</width>
		<height>480</height>
		<depth>3</depth>
	</size>
	<segmented>0</segmented>
	<object>
		<name>H</name>
		<pose>Unspecified</pose>
		<truncated>0</truncated>
		<difficult>0</difficult>
		<bndbox>
			<xmin>190</xmin>
			<ymin>117</ymin>
			<xmax>376</xmax>
			<ymax>223</ymax>
		</bndbox>
	</object>
</annotation>