<annotation>
	<folder>train</folder>
	<filename>T.d1c3f7d8-af21-11eb-9d95-00f48dddcbd4.jpg</filename>
	<path>D:\jupyternotebooks\mainsrc\Tensorflow\workspace\images\train\T.d1c3f7d8-af21-11eb-9d95-00f48dddcbd4.jpg</path>
	<source>
		<database>Unknown</database>
	</source>
	<size>
		<width>640</width>
		<height>480</height>
		<depth>3</depth>
	</size>
	<segmented>0</segmented>
	<object>
		<name>T</name>
		<pose>Unspecified</pose>
		<truncated>0</truncated>
		<difficult>0</difficult>
		<bndbox>
			<xmin>409</xmin>
			<ymin>140</ymin>
			<xmax>588</xmax>
			<ymax>353</ymax>
		</bndbox>
	</object>
</annotation>