<annotation>
	<folder>train</folder>
	<filename>W.6c42733a-af45-11eb-bfca-00f48dddcbd4.jpg</filename>
	<path>D:\jupyternotebooks\mainsrc\Tensorflow\workspace\images\train\W.6c42733a-af45-11eb-bfca-00f48dddcbd4.jpg</path>
	<source>
		<database>Unknown</database>
	</source>
	<size>
		<width>640</width>
		<height>480</height>
		<depth>3</depth>
	</size>
	<segmented>0</segmented>
	<object>
		<name>W</name>
		<pose>Unspecified</pose>
		<truncated>0</truncated>
		<difficult>0</difficult>
		<bndbox>
			<xmin>79</xmin>
			<ymin>137</ymin>
			<xmax>210</xmax>
			<ymax>342</ymax>
		</bndbox>
	</object>
</annotation>